{"pages":["SyneMono-Regular.png"],"chars":[{"id":123,"index":463,"char":"{","width":16,"height":45,"xoffset":3,"yoffset":7,"xadvance":23,"chnl":15,"x":0,"y":0,"page":0},{"id":125,"index":464,"char":"}","width":16,"height":45,"xoffset":4,"yoffset":7,"xadvance":23,"chnl":15,"x":0,"y":46,"page":0},{"id":91,"index":465,"char":"[","width":15,"height":45,"xoffset":6,"yoffset":7,"xadvance":23,"chnl":15,"x":0,"y":92,"page":0},{"id":93,"index":466,"char":"]","width":15,"height":45,"xoffset":2,"yoffset":7,"xadvance":23,"chnl":15,"x":0,"y":138,"page":0},{"id":124,"index":541,"char":"|","width":7,"height":44,"xoffset":8,"yoffset":7,"xadvance":23,"chnl":15,"x":0,"y":184,"page":0},{"id":106,"index":226,"char":"j","width":17,"height":42,"xoffset":2,"yoffset":12,"xadvance":23,"chnl":15,"x":0,"y":229,"page":0},{"id":197,"index":9,"char":"Å","width":22,"height":42,"xoffset":1,"yoffset":3,"xadvance":23,"chnl":15,"x":8,"y":184,"page":0},{"id":81,"index":75,"char":"Q","width":24,"height":40,"xoffset":-1,"yoffset":13,"xadvance":23,"chnl":15,"x":16,"y":92,"page":0},{"id":40,"index":461,"char":"(","width":13,"height":40,"xoffset":5,"yoffset":11,"xadvance":23,"chnl":15,"x":16,"y":133,"page":0},{"id":41,"index":462,"char":")","width":13,"height":40,"xoffset":5,"yoffset":11,"xadvance":23,"chnl":15,"x":30,"y":133,"page":0},{"id":220,"index":93,"char":"Ü","width":23,"height":40,"xoffset":0,"yoffset":6,"xadvance":23,"chnl":15,"x":17,"y":0,"page":0},{"id":214,"index":65,"char":"Ö","width":24,"height":40,"xoffset":-1,"yoffset":6,"xadvance":23,"chnl":15,"x":17,"y":41,"page":0},{"id":196,"index":5,"char":"Ä","width":22,"height":39,"xoffset":1,"yoffset":6,"xadvance":23,"chnl":15,"x":41,"y":0,"page":0},{"id":209,"index":61,"char":"Ñ","width":23,"height":39,"xoffset":0,"yoffset":6,"xadvance":23,"chnl":15,"x":41,"y":82,"page":0},{"id":38,"index":534,"char":"&","width":24,"height":38,"xoffset":0,"yoffset":13,"xadvance":23,"chnl":15,"x":42,"y":40,"page":0},{"id":64,"index":533,"char":"@","width":23,"height":37,"xoffset":0,"yoffset":13,"xadvance":23,"chnl":15,"x":64,"y":0,"page":0},{"id":36,"index":491,"char":"$","width":22,"height":36,"xoffset":1,"yoffset":12,"xadvance":23,"chnl":15,"x":0,"y":272,"page":0},{"id":229,"index":188,"char":"å","width":22,"height":36,"xoffset":0,"yoffset":9,"xadvance":23,"chnl":15,"x":18,"y":227,"page":0},{"id":47,"index":457,"char":"/","width":22,"height":35,"xoffset":1,"yoffset":12,"xadvance":23,"chnl":15,"x":31,"y":174,"page":0},{"id":92,"index":458,"char":"\\","width":22,"height":35,"xoffset":1,"yoffset":12,"xadvance":23,"chnl":15,"x":44,"y":122,"page":0},{"id":37,"index":520,"char":"%","width":25,"height":35,"xoffset":-1,"yoffset":12,"xadvance":23,"chnl":15,"x":65,"y":79,"page":0},{"id":112,"index":253,"char":"p","width":22,"height":34,"xoffset":1,"yoffset":20,"xadvance":23,"chnl":15,"x":67,"y":38,"page":0},{"id":113,"index":255,"char":"q","width":22,"height":34,"xoffset":0,"yoffset":20,"xadvance":23,"chnl":15,"x":88,"y":0,"page":0},{"id":100,"index":197,"char":"d","width":22,"height":34,"xoffset":0,"yoffset":12,"xadvance":23,"chnl":15,"x":90,"y":35,"page":0},{"id":103,"index":211,"char":"g","width":25,"height":34,"xoffset":0,"yoffset":20,"xadvance":23,"chnl":15,"x":111,"y":0,"page":0},{"id":98,"index":191,"char":"b","width":22,"height":34,"xoffset":1,"yoffset":12,"xadvance":23,"chnl":15,"x":0,"y":309,"page":0},{"id":252,"index":274,"char":"ü","width":22,"height":34,"xoffset":1,"yoffset":12,"xadvance":23,"chnl":15,"x":0,"y":344,"page":0},{"id":246,"index":245,"char":"ö","width":23,"height":34,"xoffset":0,"yoffset":12,"xadvance":23,"chnl":15,"x":0,"y":379,"page":0},{"id":228,"index":184,"char":"ä","width":22,"height":34,"xoffset":0,"yoffset":12,"xadvance":23,"chnl":15,"x":0,"y":414,"page":0},{"id":121,"index":287,"char":"y","width":21,"height":33,"xoffset":1,"yoffset":20,"xadvance":23,"chnl":15,"x":0,"y":449,"page":0},{"id":105,"index":217,"char":"i","width":20,"height":33,"xoffset":2,"yoffset":12,"xadvance":23,"chnl":15,"x":22,"y":449,"page":0},{"id":102,"index":210,"char":"f","width":22,"height":33,"xoffset":1,"yoffset":12,"xadvance":23,"chnl":15,"x":23,"y":414,"page":0},{"id":104,"index":215,"char":"h","width":22,"height":33,"xoffset":1,"yoffset":12,"xadvance":23,"chnl":15,"x":43,"y":448,"page":0},{"id":107,"index":227,"char":"k","width":21,"height":33,"xoffset":1,"yoffset":12,"xadvance":23,"chnl":15,"x":23,"y":264,"page":0},{"id":108,"index":229,"char":"l","width":22,"height":33,"xoffset":1,"yoffset":12,"xadvance":23,"chnl":15,"x":41,"y":210,"page":0},{"id":241,"index":241,"char":"ñ","width":22,"height":33,"xoffset":1,"yoffset":12,"xadvance":23,"chnl":15,"x":54,"y":158,"page":0},{"id":956,"index":364,"char":"μ","width":24,"height":33,"xoffset":0,"yoffset":20,"xadvance":23,"chnl":15,"x":67,"y":115,"page":0},{"id":216,"index":70,"char":"Ø","width":24,"height":33,"xoffset":-1,"yoffset":13,"xadvance":23,"chnl":15,"x":91,"y":70,"page":0},{"id":65,"index":1,"char":"A","width":22,"height":32,"xoffset":1,"yoffset":13,"xadvance":23,"chnl":15,"x":113,"y":35,"page":0},{"id":85,"index":90,"char":"U","width":23,"height":32,"xoffset":0,"yoffset":14,"xadvance":23,"chnl":15,"x":23,"y":298,"page":0},{"id":79,"index":62,"char":"O","width":24,"height":32,"xoffset":-1,"yoffset":13,"xadvance":23,"chnl":15,"x":23,"y":331,"page":0},{"id":83,"index":80,"char":"S","width":23,"height":32,"xoffset":0,"yoffset":13,"xadvance":23,"chnl":15,"x":24,"y":364,"page":0},{"id":71,"index":32,"char":"G","width":24,"height":32,"xoffset":-1,"yoffset":13,"xadvance":23,"chnl":15,"x":46,"y":397,"page":0},{"id":74,"index":46,"char":"J","width":22,"height":32,"xoffset":0,"yoffset":14,"xadvance":23,"chnl":15,"x":45,"y":244,"page":0},{"id":67,"index":13,"char":"C","width":24,"height":32,"xoffset":-1,"yoffset":13,"xadvance":23,"chnl":15,"x":64,"y":192,"page":0},{"id":56,"index":374,"char":"8","width":22,"height":32,"xoffset":1,"yoffset":13,"xadvance":23,"chnl":15,"x":77,"y":149,"page":0},{"id":57,"index":375,"char":"9","width":22,"height":32,"xoffset":1,"yoffset":13,"xadvance":23,"chnl":15,"x":92,"y":104,"page":0},{"id":53,"index":371,"char":"5","width":21,"height":32,"xoffset":1,"yoffset":14,"xadvance":23,"chnl":15,"x":47,"y":277,"page":0},{"id":54,"index":372,"char":"6","width":22,"height":32,"xoffset":1,"yoffset":14,"xadvance":23,"chnl":15,"x":68,"y":225,"page":0},{"id":50,"index":368,"char":"2","width":20,"height":32,"xoffset":2,"yoffset":13,"xadvance":23,"chnl":15,"x":89,"y":182,"page":0},{"id":51,"index":369,"char":"3","width":20,"height":32,"xoffset":1,"yoffset":13,"xadvance":23,"chnl":15,"x":100,"y":137,"page":0},{"id":48,"index":366,"char":"0","width":23,"height":32,"xoffset":0,"yoffset":13,"xadvance":23,"chnl":15,"x":115,"y":104,"page":0},{"id":63,"index":451,"char":"?","width":20,"height":32,"xoffset":1,"yoffset":13,"xadvance":23,"chnl":15,"x":116,"y":68,"page":0},{"id":163,"index":494,"char":"£","width":20,"height":32,"xoffset":1,"yoffset":13,"xadvance":23,"chnl":15,"x":136,"y":35,"page":0},{"id":8364,"index":492,"char":"€","width":25,"height":32,"xoffset":-2,"yoffset":13,"xadvance":23,"chnl":15,"x":137,"y":0,"page":0},{"id":937,"index":363,"char":"Ω","width":25,"height":32,"xoffset":-1,"yoffset":13,"xadvance":23,"chnl":15,"x":137,"y":68,"page":0},{"id":90,"index":111,"char":"Z","width":22,"height":31,"xoffset":0,"yoffset":14,"xadvance":23,"chnl":15,"x":157,"y":33,"page":0},{"id":69,"index":22,"char":"E","width":23,"height":31,"xoffset":0,"yoffset":14,"xadvance":23,"chnl":15,"x":163,"y":0,"page":0},{"id":82,"index":76,"char":"R","width":23,"height":31,"xoffset":0,"yoffset":14,"xadvance":23,"chnl":15,"x":66,"y":430,"page":0},{"id":84,"index":85,"char":"T","width":26,"height":31,"xoffset":-1,"yoffset":14,"xadvance":23,"chnl":15,"x":66,"y":462,"page":0},{"id":89,"index":106,"char":"Y","width":22,"height":31,"xoffset":0,"yoffset":14,"xadvance":23,"chnl":15,"x":48,"y":310,"page":0},{"id":73,"index":38,"char":"I","width":18,"height":31,"xoffset":2,"yoffset":14,"xadvance":23,"chnl":15,"x":69,"y":258,"page":0},{"id":80,"index":73,"char":"P","width":24,"height":31,"xoffset":0,"yoffset":14,"xadvance":23,"chnl":15,"x":48,"y":342,"page":0},{"id":68,"index":18,"char":"D","width":24,"height":31,"xoffset":0,"yoffset":14,"xadvance":23,"chnl":15,"x":71,"y":290,"page":0},{"id":70,"index":31,"char":"F","width":23,"height":31,"xoffset":0,"yoffset":14,"xadvance":23,"chnl":15,"x":88,"y":258,"page":0},{"id":72,"index":36,"char":"H","width":23,"height":31,"xoffset":0,"yoffset":14,"xadvance":23,"chnl":15,"x":91,"y":215,"page":0},{"id":75,"index":47,"char":"K","width":23,"height":31,"xoffset":0,"yoffset":14,"xadvance":23,"chnl":15,"x":110,"y":170,"page":0},{"id":76,"index":49,"char":"L","width":23,"height":31,"xoffset":0,"yoffset":14,"xadvance":23,"chnl":15,"x":121,"y":137,"page":0},{"id":77,"index":55,"char":"M","width":23,"height":31,"xoffset":0,"yoffset":14,"xadvance":23,"chnl":15,"x":139,"y":101,"page":0},{"id":87,"index":100,"char":"W","width":23,"height":31,"xoffset":0,"yoffset":14,"xadvance":23,"chnl":15,"x":71,"y":374,"page":0},{"id":88,"index":105,"char":"X","width":21,"height":31,"xoffset":1,"yoffset":14,"xadvance":23,"chnl":15,"x":73,"y":322,"page":0},{"id":86,"index":99,"char":"V","width":23,"height":31,"xoffset":0,"yoffset":14,"xadvance":23,"chnl":15,"x":90,"y":406,"page":0},{"id":66,"index":12,"char":"B","width":23,"height":31,"xoffset":0,"yoffset":14,"xadvance":23,"chnl":15,"x":93,"y":438,"page":0},{"id":78,"index":56,"char":"N","width":23,"height":31,"xoffset":0,"yoffset":14,"xadvance":23,"chnl":15,"x":93,"y":470,"page":0},{"id":55,"index":373,"char":"7","width":20,"height":31,"xoffset":2,"yoffset":14,"xadvance":23,"chnl":15,"x":95,"y":322,"page":0},{"id":52,"index":370,"char":"4","width":23,"height":31,"xoffset":0,"yoffset":14,"xadvance":23,"chnl":15,"x":96,"y":290,"page":0},{"id":49,"index":367,"char":"1","width":20,"height":31,"xoffset":1,"yoffset":14,"xadvance":23,"chnl":15,"x":112,"y":247,"page":0},{"id":33,"index":449,"char":"!","width":8,"height":31,"xoffset":7,"yoffset":14,"xadvance":23,"chnl":15,"x":115,"y":202,"page":0},{"id":198,"index":11,"char":"Æ","width":22,"height":31,"xoffset":1,"yoffset":14,"xadvance":23,"chnl":15,"x":124,"y":202,"page":0},{"id":116,"index":266,"char":"t","width":21,"height":30,"xoffset":1,"yoffset":15,"xadvance":23,"chnl":15,"x":43,"y":482,"page":0},{"id":35,"index":456,"char":"#","width":24,"height":30,"xoffset":0,"yoffset":15,"xadvance":23,"chnl":15,"x":134,"y":169,"page":0},{"id":59,"index":447,"char":";","width":9,"height":29,"xoffset":7,"yoffset":21,"xadvance":23,"chnl":15,"x":0,"y":483,"page":0},{"id":97,"index":180,"char":"a","width":22,"height":26,"xoffset":0,"yoffset":20,"xadvance":23,"chnl":15,"x":10,"y":483,"page":0},{"id":101,"index":201,"char":"e","width":23,"height":26,"xoffset":0,"yoffset":20,"xadvance":23,"chnl":15,"x":145,"y":133,"page":0},{"id":111,"index":242,"char":"o","width":23,"height":26,"xoffset":0,"yoffset":20,"xadvance":23,"chnl":15,"x":95,"y":354,"page":0},{"id":115,"index":260,"char":"s","width":22,"height":26,"xoffset":1,"yoffset":20,"xadvance":23,"chnl":15,"x":116,"y":322,"page":0},{"id":99,"index":192,"char":"c","width":22,"height":26,"xoffset":0,"yoffset":20,"xadvance":23,"chnl":15,"x":120,"y":279,"page":0},{"id":230,"index":190,"char":"æ","width":25,"height":26,"xoffset":-1,"yoffset":20,"xadvance":23,"chnl":15,"x":133,"y":234,"page":0},{"id":248,"index":250,"char":"ø","width":23,"height":26,"xoffset":0,"yoffset":19,"xadvance":23,"chnl":15,"x":147,"y":200,"page":0},{"id":122,"index":292,"char":"z","width":21,"height":25,"xoffset":1,"yoffset":20,"xadvance":23,"chnl":15,"x":159,"y":160,"page":0},{"id":114,"index":256,"char":"r","width":21,"height":25,"xoffset":1,"yoffset":20,"xadvance":23,"chnl":15,"x":114,"y":381,"page":0},{"id":117,"index":271,"char":"u","width":22,"height":25,"xoffset":1,"yoffset":20,"xadvance":23,"chnl":15,"x":114,"y":407,"page":0},{"id":109,"index":235,"char":"m","width":24,"height":25,"xoffset":-1,"yoffset":20,"xadvance":23,"chnl":15,"x":119,"y":349,"page":0},{"id":119,"index":281,"char":"w","width":22,"height":25,"xoffset":1,"yoffset":20,"xadvance":23,"chnl":15,"x":136,"y":375,"page":0},{"id":120,"index":286,"char":"x","width":21,"height":25,"xoffset":1,"yoffset":20,"xadvance":23,"chnl":15,"x":139,"y":306,"page":0},{"id":118,"index":280,"char":"v","width":21,"height":25,"xoffset":1,"yoffset":20,"xadvance":23,"chnl":15,"x":144,"y":332,"page":0},{"id":110,"index":236,"char":"n","width":22,"height":25,"xoffset":1,"yoffset":20,"xadvance":23,"chnl":15,"x":143,"y":261,"page":0},{"id":960,"index":365,"char":"π","width":24,"height":25,"xoffset":0,"yoffset":20,"xadvance":23,"chnl":15,"x":159,"y":227,"page":0},{"id":916,"index":362,"char":"Δ","width":17,"height":25,"xoffset":4,"yoffset":20,"xadvance":23,"chnl":15,"x":171,"y":186,"page":0},{"id":58,"index":446,"char":":","width":8,"height":24,"xoffset":7,"yoffset":21,"xadvance":23,"chnl":15,"x":95,"y":381,"page":0},{"id":95,"index":473,"char":"_","width":24,"height":7,"xoffset":0,"yoffset":46,"xadvance":23,"chnl":15,"x":159,"y":253,"page":0},{"id":8211,"index":471,"char":"–","width":21,"height":7,"xoffset":1,"yoffset":28,"xadvance":23,"chnl":15,"x":24,"y":397,"page":0},{"id":61,"index":501,"char":"=","width":20,"height":15,"xoffset":1,"yoffset":24,"xadvance":23,"chnl":15,"x":73,"y":354,"page":0},{"id":43,"index":497,"char":"+","width":19,"height":19,"xoffset":2,"yoffset":22,"xadvance":23,"chnl":15,"x":48,"y":374,"page":0},{"id":42,"index":455,"char":"*","width":17,"height":17,"xoffset":3,"yoffset":11,"xadvance":23,"chnl":15,"x":46,"y":430,"page":0},{"id":45,"index":469,"char":"-","width":16,"height":7,"xoffset":3,"yoffset":28,"xadvance":23,"chnl":15,"x":115,"y":234,"page":0},{"id":176,"index":540,"char":"°","width":15,"height":15,"xoffset":4,"yoffset":13,"xadvance":23,"chnl":15,"x":120,"y":306,"page":0},{"id":34,"index":484,"char":"\"","width":14,"height":13,"xoffset":4,"yoffset":14,"xadvance":23,"chnl":15,"x":171,"y":212,"page":0},{"id":1040,"index":0,"char":"А","width":14,"height":14,"xoffset":4,"yoffset":25,"xadvance":23,"chnl":15,"x":144,"y":358,"page":0},{"id":1072,"index":0,"char":"а","width":14,"height":14,"xoffset":4,"yoffset":25,"xadvance":23,"chnl":15,"x":71,"y":406,"page":0},{"id":1041,"index":0,"char":"Б","width":14,"height":14,"xoffset":4,"yoffset":25,"xadvance":23,"chnl":15,"x":65,"y":494,"page":0},{"id":1073,"index":0,"char":"б","width":14,"height":14,"xoffset":4,"yoffset":25,"xadvance":23,"chnl":15,"x":143,"y":287,"page":0},{"id":1042,"index":0,"char":"В","width":14,"height":14,"xoffset":4,"yoffset":25,"xadvance":23,"chnl":15,"x":158,"y":287,"page":0},{"id":1074,"index":0,"char":"в","width":14,"height":14,"xoffset":4,"yoffset":25,"xadvance":23,"chnl":15,"x":166,"y":261,"page":0},{"id":1043,"index":0,"char":"Г","width":14,"height":14,"xoffset":4,"yoffset":25,"xadvance":23,"chnl":15,"x":161,"y":302,"page":0},{"id":1075,"index":0,"char":"г","width":14,"height":14,"xoffset":4,"yoffset":25,"xadvance":23,"chnl":15,"x":161,"y":317,"page":0},{"id":1044,"index":0,"char":"Д","width":14,"height":14,"xoffset":4,"yoffset":25,"xadvance":23,"chnl":15,"x":173,"y":276,"page":0},{"id":1076,"index":0,"char":"д","width":14,"height":14,"xoffset":4,"yoffset":25,"xadvance":23,"chnl":15,"x":181,"y":261,"page":0},{"id":1045,"index":0,"char":"Е","width":14,"height":14,"xoffset":4,"yoffset":25,"xadvance":23,"chnl":15,"x":184,"y":226,"page":0},{"id":1077,"index":0,"char":"е","width":14,"height":14,"xoffset":4,"yoffset":25,"xadvance":23,"chnl":15,"x":184,"y":241,"page":0},{"id":1025,"index":0,"char":"Ё","width":14,"height":14,"xoffset":4,"yoffset":25,"xadvance":23,"chnl":15,"x":163,"y":65,"page":0},{"id":1105,"index":0,"char":"ё","width":14,"height":14,"xoffset":4,"yoffset":25,"xadvance":23,"chnl":15,"x":163,"y":80,"page":0},{"id":1046,"index":0,"char":"Ж","width":14,"height":14,"xoffset":4,"yoffset":25,"xadvance":23,"chnl":15,"x":163,"y":95,"page":0},{"id":1078,"index":0,"char":"ж","width":14,"height":14,"xoffset":4,"yoffset":25,"xadvance":23,"chnl":15,"x":163,"y":110,"page":0},{"id":1047,"index":0,"char":"З","width":14,"height":14,"xoffset":4,"yoffset":25,"xadvance":23,"chnl":15,"x":169,"y":125,"page":0},{"id":1079,"index":0,"char":"з","width":14,"height":14,"xoffset":4,"yoffset":25,"xadvance":23,"chnl":15,"x":169,"y":140,"page":0},{"id":1048,"index":0,"char":"И","width":14,"height":14,"xoffset":4,"yoffset":25,"xadvance":23,"chnl":15,"x":181,"y":155,"page":0},{"id":1080,"index":0,"char":"и","width":14,"height":14,"xoffset":4,"yoffset":25,"xadvance":23,"chnl":15,"x":181,"y":170,"page":0},{"id":1049,"index":0,"char":"Й","width":14,"height":14,"xoffset":4,"yoffset":25,"xadvance":23,"chnl":15,"x":189,"y":185,"page":0},{"id":1081,"index":0,"char":"й","width":14,"height":14,"xoffset":4,"yoffset":25,"xadvance":23,"chnl":15,"x":189,"y":200,"page":0},{"id":1050,"index":0,"char":"К","width":14,"height":14,"xoffset":4,"yoffset":25,"xadvance":23,"chnl":15,"x":178,"y":65,"page":0},{"id":1082,"index":0,"char":"к","width":14,"height":14,"xoffset":4,"yoffset":25,"xadvance":23,"chnl":15,"x":180,"y":32,"page":0},{"id":1051,"index":0,"char":"Л","width":14,"height":14,"xoffset":4,"yoffset":25,"xadvance":23,"chnl":15,"x":180,"y":47,"page":0},{"id":1083,"index":0,"char":"л","width":14,"height":14,"xoffset":4,"yoffset":25,"xadvance":23,"chnl":15,"x":187,"y":0,"page":0},{"id":1052,"index":0,"char":"М","width":14,"height":14,"xoffset":4,"yoffset":25,"xadvance":23,"chnl":15,"x":187,"y":15,"page":0},{"id":1084,"index":0,"char":"м","width":14,"height":14,"xoffset":4,"yoffset":25,"xadvance":23,"chnl":15,"x":178,"y":80,"page":0},{"id":1053,"index":0,"char":"Н","width":14,"height":14,"xoffset":4,"yoffset":25,"xadvance":23,"chnl":15,"x":178,"y":95,"page":0},{"id":1085,"index":0,"char":"н","width":14,"height":14,"xoffset":4,"yoffset":25,"xadvance":23,"chnl":15,"x":178,"y":110,"page":0},{"id":1054,"index":0,"char":"О","width":14,"height":14,"xoffset":4,"yoffset":25,"xadvance":23,"chnl":15,"x":184,"y":125,"page":0},{"id":1086,"index":0,"char":"о","width":14,"height":14,"xoffset":4,"yoffset":25,"xadvance":23,"chnl":15,"x":184,"y":140,"page":0},{"id":1055,"index":0,"char":"П","width":14,"height":14,"xoffset":4,"yoffset":25,"xadvance":23,"chnl":15,"x":196,"y":155,"page":0},{"id":1087,"index":0,"char":"п","width":14,"height":14,"xoffset":4,"yoffset":25,"xadvance":23,"chnl":15,"x":196,"y":170,"page":0},{"id":1056,"index":0,"char":"Р","width":14,"height":14,"xoffset":4,"yoffset":25,"xadvance":23,"chnl":15,"x":193,"y":62,"page":0},{"id":1088,"index":0,"char":"р","width":14,"height":14,"xoffset":4,"yoffset":25,"xadvance":23,"chnl":15,"x":195,"y":30,"page":0},{"id":1057,"index":0,"char":"С","width":14,"height":14,"xoffset":4,"yoffset":25,"xadvance":23,"chnl":15,"x":195,"y":45,"page":0},{"id":1089,"index":0,"char":"с","width":14,"height":14,"xoffset":4,"yoffset":25,"xadvance":23,"chnl":15,"x":202,"y":0,"page":0},{"id":1058,"index":0,"char":"Т","width":14,"height":14,"xoffset":4,"yoffset":25,"xadvance":23,"chnl":15,"x":202,"y":15,"page":0},{"id":1090,"index":0,"char":"т","width":14,"height":14,"xoffset":4,"yoffset":25,"xadvance":23,"chnl":15,"x":193,"y":77,"page":0},{"id":1059,"index":0,"char":"У","width":14,"height":14,"xoffset":4,"yoffset":25,"xadvance":23,"chnl":15,"x":193,"y":92,"page":0},{"id":1091,"index":0,"char":"у","width":14,"height":14,"xoffset":4,"yoffset":25,"xadvance":23,"chnl":15,"x":193,"y":107,"page":0},{"id":1060,"index":0,"char":"Ф","width":14,"height":14,"xoffset":4,"yoffset":25,"xadvance":23,"chnl":15,"x":199,"y":122,"page":0},{"id":1092,"index":0,"char":"ф","width":14,"height":14,"xoffset":4,"yoffset":25,"xadvance":23,"chnl":15,"x":199,"y":137,"page":0},{"id":1061,"index":0,"char":"Х","width":14,"height":14,"xoffset":4,"yoffset":25,"xadvance":23,"chnl":15,"x":208,"y":60,"page":0},{"id":1093,"index":0,"char":"х","width":14,"height":14,"xoffset":4,"yoffset":25,"xadvance":23,"chnl":15,"x":210,"y":30,"page":0},{"id":1062,"index":0,"char":"Ц","width":14,"height":14,"xoffset":4,"yoffset":25,"xadvance":23,"chnl":15,"x":210,"y":45,"page":0},{"id":1094,"index":0,"char":"ц","width":14,"height":14,"xoffset":4,"yoffset":25,"xadvance":23,"chnl":15,"x":217,"y":0,"page":0},{"id":1063,"index":0,"char":"Ч","width":14,"height":14,"xoffset":4,"yoffset":25,"xadvance":23,"chnl":15,"x":217,"y":15,"page":0},{"id":1095,"index":0,"char":"ч","width":14,"height":14,"xoffset":4,"yoffset":25,"xadvance":23,"chnl":15,"x":208,"y":75,"page":0},{"id":1064,"index":0,"char":"Ш","width":14,"height":14,"xoffset":4,"yoffset":25,"xadvance":23,"chnl":15,"x":208,"y":90,"page":0},{"id":1096,"index":0,"char":"ш","width":14,"height":14,"xoffset":4,"yoffset":25,"xadvance":23,"chnl":15,"x":208,"y":105,"page":0},{"id":1065,"index":0,"char":"Щ","width":14,"height":14,"xoffset":4,"yoffset":25,"xadvance":23,"chnl":15,"x":117,"y":433,"page":0},{"id":1097,"index":0,"char":"щ","width":14,"height":14,"xoffset":4,"yoffset":25,"xadvance":23,"chnl":15,"x":117,"y":448,"page":0},{"id":1066,"index":0,"char":"Ъ","width":14,"height":14,"xoffset":4,"yoffset":25,"xadvance":23,"chnl":15,"x":117,"y":463,"page":0},{"id":1098,"index":0,"char":"ъ","width":14,"height":14,"xoffset":4,"yoffset":25,"xadvance":23,"chnl":15,"x":117,"y":478,"page":0},{"id":1067,"index":0,"char":"Ы","width":14,"height":14,"xoffset":4,"yoffset":25,"xadvance":23,"chnl":15,"x":117,"y":493,"page":0},{"id":1099,"index":0,"char":"ы","width":14,"height":14,"xoffset":4,"yoffset":25,"xadvance":23,"chnl":15,"x":132,"y":433,"page":0},{"id":1068,"index":0,"char":"Ь","width":14,"height":14,"xoffset":4,"yoffset":25,"xadvance":23,"chnl":15,"x":137,"y":401,"page":0},{"id":1100,"index":0,"char":"ь","width":14,"height":14,"xoffset":4,"yoffset":25,"xadvance":23,"chnl":15,"x":137,"y":416,"page":0},{"id":1069,"index":0,"char":"Э","width":14,"height":14,"xoffset":4,"yoffset":25,"xadvance":23,"chnl":15,"x":132,"y":448,"page":0},{"id":1101,"index":0,"char":"э","width":14,"height":14,"xoffset":4,"yoffset":25,"xadvance":23,"chnl":15,"x":132,"y":463,"page":0},{"id":1070,"index":0,"char":"Ю","width":14,"height":14,"xoffset":4,"yoffset":25,"xadvance":23,"chnl":15,"x":132,"y":478,"page":0},{"id":1102,"index":0,"char":"ю","width":14,"height":14,"xoffset":4,"yoffset":25,"xadvance":23,"chnl":15,"x":132,"y":493,"page":0},{"id":1071,"index":0,"char":"Я","width":14,"height":14,"xoffset":4,"yoffset":25,"xadvance":23,"chnl":15,"x":147,"y":431,"page":0},{"id":1103,"index":0,"char":"я","width":14,"height":14,"xoffset":4,"yoffset":25,"xadvance":23,"chnl":15,"x":152,"y":401,"page":0},{"id":962,"index":0,"char":"ς","width":14,"height":14,"xoffset":4,"yoffset":25,"xadvance":23,"chnl":15,"x":152,"y":416,"page":0},{"id":949,"index":0,"char":"ε","width":14,"height":14,"xoffset":4,"yoffset":25,"xadvance":23,"chnl":15,"x":159,"y":358,"page":0},{"id":961,"index":0,"char":"ρ","width":14,"height":14,"xoffset":4,"yoffset":25,"xadvance":23,"chnl":15,"x":166,"y":332,"page":0},{"id":964,"index":0,"char":"τ","width":14,"height":14,"xoffset":4,"yoffset":25,"xadvance":23,"chnl":15,"x":159,"y":373,"page":0},{"id":965,"index":0,"char":"υ","width":14,"height":14,"xoffset":4,"yoffset":25,"xadvance":23,"chnl":15,"x":176,"y":291,"page":0},{"id":952,"index":0,"char":"θ","width":14,"height":14,"xoffset":4,"yoffset":25,"xadvance":23,"chnl":15,"x":188,"y":276,"page":0},{"id":953,"index":0,"char":"ι","width":14,"height":14,"xoffset":4,"yoffset":25,"xadvance":23,"chnl":15,"x":196,"y":256,"page":0},{"id":959,"index":0,"char":"ο","width":14,"height":14,"xoffset":4,"yoffset":25,"xadvance":23,"chnl":15,"x":176,"y":306,"page":0},{"id":945,"index":0,"char":"α","width":14,"height":14,"xoffset":4,"yoffset":25,"xadvance":23,"chnl":15,"x":199,"y":215,"page":0},{"id":963,"index":0,"char":"σ","width":14,"height":14,"xoffset":4,"yoffset":25,"xadvance":23,"chnl":15,"x":199,"y":230,"page":0},{"id":948,"index":0,"char":"δ","width":14,"height":14,"xoffset":4,"yoffset":25,"xadvance":23,"chnl":15,"x":204,"y":185,"page":0},{"id":966,"index":0,"char":"φ","width":14,"height":14,"xoffset":4,"yoffset":25,"xadvance":23,"chnl":15,"x":204,"y":200,"page":0},{"id":947,"index":0,"char":"γ","width":14,"height":14,"xoffset":4,"yoffset":25,"xadvance":23,"chnl":15,"x":211,"y":152,"page":0},{"id":951,"index":0,"char":"η","width":14,"height":14,"xoffset":4,"yoffset":25,"xadvance":23,"chnl":15,"x":211,"y":167,"page":0},{"id":958,"index":0,"char":"ξ","width":14,"height":14,"xoffset":4,"yoffset":25,"xadvance":23,"chnl":15,"x":214,"y":120,"page":0},{"id":954,"index":0,"char":"κ","width":14,"height":14,"xoffset":4,"yoffset":25,"xadvance":23,"chnl":15,"x":214,"y":135,"page":0},{"id":955,"index":0,"char":"λ","width":14,"height":14,"xoffset":4,"yoffset":25,"xadvance":23,"chnl":15,"x":223,"y":60,"page":0},{"id":950,"index":0,"char":"ζ","width":14,"height":14,"xoffset":4,"yoffset":25,"xadvance":23,"chnl":15,"x":225,"y":30,"page":0},{"id":967,"index":0,"char":"χ","width":14,"height":14,"xoffset":4,"yoffset":25,"xadvance":23,"chnl":15,"x":225,"y":45,"page":0},{"id":968,"index":0,"char":"ψ","width":14,"height":14,"xoffset":4,"yoffset":25,"xadvance":23,"chnl":15,"x":232,"y":0,"page":0},{"id":969,"index":0,"char":"ω","width":14,"height":14,"xoffset":4,"yoffset":25,"xadvance":23,"chnl":15,"x":232,"y":15,"page":0},{"id":946,"index":0,"char":"β","width":14,"height":14,"xoffset":4,"yoffset":25,"xadvance":23,"chnl":15,"x":223,"y":75,"page":0},{"id":957,"index":0,"char":"ν","width":14,"height":14,"xoffset":4,"yoffset":25,"xadvance":23,"chnl":15,"x":223,"y":90,"page":0},{"id":917,"index":0,"char":"Ε","width":14,"height":14,"xoffset":4,"yoffset":25,"xadvance":23,"chnl":15,"x":223,"y":105,"page":0},{"id":929,"index":0,"char":"Ρ","width":14,"height":14,"xoffset":4,"yoffset":25,"xadvance":23,"chnl":15,"x":147,"y":446,"page":0},{"id":932,"index":0,"char":"Τ","width":14,"height":14,"xoffset":4,"yoffset":25,"xadvance":23,"chnl":15,"x":147,"y":461,"page":0},{"id":933,"index":0,"char":"Υ","width":14,"height":14,"xoffset":4,"yoffset":25,"xadvance":23,"chnl":15,"x":147,"y":476,"page":0},{"id":920,"index":0,"char":"Θ","width":14,"height":14,"xoffset":4,"yoffset":25,"xadvance":23,"chnl":15,"x":147,"y":491,"page":0},{"id":921,"index":0,"char":"Ι","width":14,"height":14,"xoffset":4,"yoffset":25,"xadvance":23,"chnl":15,"x":162,"y":431,"page":0},{"id":927,"index":0,"char":"Ο","width":14,"height":14,"xoffset":4,"yoffset":25,"xadvance":23,"chnl":15,"x":167,"y":388,"page":0},{"id":928,"index":0,"char":"Π","width":14,"height":14,"xoffset":4,"yoffset":25,"xadvance":23,"chnl":15,"x":167,"y":403,"page":0},{"id":913,"index":0,"char":"Α","width":14,"height":14,"xoffset":4,"yoffset":25,"xadvance":23,"chnl":15,"x":174,"y":347,"page":0},{"id":931,"index":0,"char":"Σ","width":14,"height":14,"xoffset":4,"yoffset":25,"xadvance":23,"chnl":15,"x":181,"y":321,"page":0},{"id":934,"index":0,"char":"Φ","width":14,"height":14,"xoffset":4,"yoffset":25,"xadvance":23,"chnl":15,"x":174,"y":362,"page":0},{"id":915,"index":0,"char":"Γ","width":14,"height":14,"xoffset":4,"yoffset":25,"xadvance":23,"chnl":15,"x":191,"y":291,"page":0},{"id":919,"index":0,"char":"Η","width":14,"height":14,"xoffset":4,"yoffset":25,"xadvance":23,"chnl":15,"x":191,"y":306,"page":0},{"id":926,"index":0,"char":"Ξ","width":14,"height":14,"xoffset":4,"yoffset":25,"xadvance":23,"chnl":15,"x":203,"y":271,"page":0},{"id":922,"index":0,"char":"Κ","width":14,"height":14,"xoffset":4,"yoffset":25,"xadvance":23,"chnl":15,"x":211,"y":245,"page":0},{"id":923,"index":0,"char":"Λ","width":14,"height":14,"xoffset":4,"yoffset":25,"xadvance":23,"chnl":15,"x":214,"y":215,"page":0},{"id":918,"index":0,"char":"Ζ","width":14,"height":14,"xoffset":4,"yoffset":25,"xadvance":23,"chnl":15,"x":214,"y":230,"page":0},{"id":935,"index":0,"char":"Χ","width":14,"height":14,"xoffset":4,"yoffset":25,"xadvance":23,"chnl":15,"x":219,"y":182,"page":0},{"id":936,"index":0,"char":"Ψ","width":14,"height":14,"xoffset":4,"yoffset":25,"xadvance":23,"chnl":15,"x":219,"y":197,"page":0},{"id":914,"index":0,"char":"Β","width":14,"height":14,"xoffset":4,"yoffset":25,"xadvance":23,"chnl":15,"x":226,"y":150,"page":0},{"id":925,"index":0,"char":"Ν","width":14,"height":14,"xoffset":4,"yoffset":25,"xadvance":23,"chnl":15,"x":226,"y":165,"page":0},{"id":924,"index":0,"char":"Μ","width":14,"height":14,"xoffset":4,"yoffset":25,"xadvance":23,"chnl":15,"x":229,"y":120,"page":0},{"id":44,"index":445,"char":",","width":9,"height":12,"xoffset":7,"yoffset":37,"xadvance":23,"chnl":15,"x":31,"y":210,"page":0},{"id":39,"index":485,"char":"'","width":9,"height":12,"xoffset":7,"yoffset":14,"xadvance":23,"chnl":15,"x":44,"y":158,"page":0},{"id":46,"index":444,"char":".","width":8,"height":8,"xoffset":7,"yoffset":37,"xadvance":23,"chnl":15,"x":67,"y":149,"page":0},{"id":126,"index":509,"char":"~","width":8,"height":8,"xoffset":7,"yoffset":27,"xadvance":23,"chnl":15,"x":145,"y":160,"page":0}],"info":{"face":"SyneMono-Regular","size":42,"bold":0,"italic":0,"charset":["a","z","e","r","t","y","u","i","o","p","q","s","d","f","g","h","j","k","l","m","w","x","c","v","b","n","A","Z","E","R","T","Y","U","I","O","P","Q","S","D","F","G","H","J","K","L","M","W","X","C","V","B","N","/","\\","*","-","–","+","7","8","9","4","5","6","1","2","3","0",",",";",":","!","?",".","%","$","£","€","=","{","}","(",")","[","]","&","~","\"","'","#","_","|","°","@","А","а","Б","б","В","в","Г","г","Д","д","Е","е","Ё","ё","Ж","ж","З","з","И","и","Й","й","К","к","Л","л","М","м","Н","н","О","о","П","п","Р","р","С","с","Т","т","У","у","Ф","ф","Х","х","Ц","ц","Ч","ч","Ш","ш","Щ","щ","Ъ","ъ","Ы","ы","Ь","ь","Э","э","Ю","ю","Я","я","ü","Ü","ö","Ö","ä","Ä","ñ","Ñ","ς","ε","ρ","τ","υ","θ","ι","ο","π","α","σ","δ","φ","γ","η","ξ","κ","λ","ζ","χ","ψ","ω","β","ν","μ","Ε","Ρ","Τ","Υ","Θ","Ι","Ο","Π","Α","Σ","Δ","Φ","Γ","Η","Ξ","Κ","Λ","Ζ","Χ","Ψ","Ω","Β","Ν","Μ","å","Å","æ","Æ","ø","Ø"],"unicode":1,"stretchH":100,"smooth":1,"aa":1,"padding":[2,2,2,2],"spacing":[0,0]},"common":{"lineHeight":50,"base":41,"scaleW":512,"scaleH":512,"pages":1,"packed":0,"alphaChnl":0,"redChnl":0,"greenChnl":0,"blueChnl":0},"distanceField":{"fieldType":"msdf","distanceRange":4},"kernings":[]}